[
 {
  "part_number": "LR001247"
 },
 {
  "part_number": "LR013148"
 },
 {
  "part_number": "TYF500030"
 },
 {
  "part_number": "LR068126"
 },
 {
  "part_number": "LR001381"
 },
 {
  "part_number": "LR001313"
 },
 {
  "part_number": "LR009705"
 },
 {
  "part_number": "ANR2224"
 },
 {
  "part_number": "LR022896"
 },
 {
  "part_number": "LR106277"
 },
 {
  "part_number": "IYK500010"
 },
 {
  "part_number": "LR054612"
 },
 {
  "part_number": "LR033163"
 },
 {
  "part_number": "LR032818"
 },
 {
  "part_number": "LR011279"
 },
 {
  "part_number": "1311289"
 },
 {
  "part_number": "LR113358"
 },
 {
  "part_number": "LR038815"
 },
 {
  "part_number": "LR000893"
 },
 {
  "part_number": "LR011593"
 },
 {
  "part_number": "STC50519"
 },
 {
  "part_number": "1316152"
 },
 {
  "part_number": "DYC500030"
 },
 {
  "part_number": "WYP000025"
 },
 {
  "part_number": "STC50550"
 },
 {
  "part_number": "TYK500010"
 },
 {
  "part_number": "LR037089"
 },
 {
  "part_number": "LR033144"
 },
 {
  "part_number": "RDI000034"
 },
 {
  "part_number": "LR032080"
 },
 {
  "part_number": "LR041978"
 },
 {
  "part_number": "IPN500050"
 },
 {
  "part_number": "LR027255"
 },
 {
  "part_number": "LR053837"
 },
 {
  "part_number": "LR056138"
 },
 {
  "part_number": "LR000869"
 },
 {
  "part_number": "LR023440"
 },
 {
  "part_number": "LR072610"
 },
 {
  "part_number": "LR073366"
 },
 {
  "part_number": "LR032644"
 },
 {
  "part_number": "LR013135"
 },
 {
  "part_number": "LR003915"
 },
 {
  "part_number": "LR000881"
 },
 {
  "part_number": "LR002461"
 },
 {
  "part_number": "LR002338"
 },
 {
  "part_number": "LR019897"
 },
 {
  "part_number": "LR007055"
 },
 {
  "part_number": "LR036369"
 },
 {
  "part_number": "LR054941"
 },
 {
  "part_number": "DZM000070"
 },
 {
  "part_number": "LR002888"
 },
 {
  "part_number": "LR019727"
 },
 {
  "part_number": "LR048451"
 },
 {
  "part_number": "SDB000624"
 },
 {
  "part_number": "LR024316"
 },
 {
  "part_number": "LR050538"
 },
 {
  "part_number": "LR003137"
 },
 {
  "part_number": "LR008353"
 },
 {
  "part_number": "LR001302"
 },
 {
  "part_number": "1331316"
 },
 {
  "part_number": "LR019118"
 },
 {
  "part_number": "LR073675"
 },
 {
  "part_number": "LR003401"
 },
 {
  "part_number": "LR054836"
 },
 {
  "part_number": "RVU500011"
 },
 {
  "part_number": "LR097986"
 },
 {
  "part_number": "LR000801"
 },
 {
  "part_number": "SDB000646"
 },
 {
  "part_number": "LR025048"
 },
 {
  "part_number": "LR031439"
 },
 {
  "part_number": "LR073669"
 },
 {
  "part_number": "DYC101420"
 },
 {
  "part_number": "LR011220"
 },
 {
  "part_number": "LR004153"
 },
 {
  "part_number": "1354289"
 },
 {
  "part_number": "KYG500380"
 },
 {
  "part_number": "RYQ500070"
 },
 {
  "part_number": "LR023145"
 },
 {
  "part_number": "LR096524"
 },
 {
  "part_number": "LR085485"
 },
 {
  "part_number": "RVU000022"
 },
 {
  "part_number": "LR025680"
 },
 {
  "part_number": "LR014345"
 },
 {
  "part_number": "FT110206"
 },
 {
  "part_number": "1372726"
 },
 {
  "part_number": "YWK10003L"
 },
 {
  "part_number": "LR050541"
 },
 {
  "part_number": "LR018345"
 },
 {
  "part_number": "SYH500040"
 },
 {
  "part_number": "LR005253"
 },
 {
  "part_number": "LR030846"
 },
 {
  "part_number": "LR117068"
 },
 {
  "part_number": "LR122585"
 },
 {
  "part_number": "LR055291"
 },
 {
  "part_number": "LR044836"
 },
 {
  "part_number": "LR002906"
 },
 {
  "part_number": "DYR500010"
 },
 {
  "part_number": "LR004141"
 },
 {
  "part_number": "1357627"
 },
 {
  "part_number": "AYH100790"
 },
 {
  "part_number": "LR108260"
 },
 {
  "part_number": "LR023442"
 },
 {
  "part_number": "LR005816"
 },
 {
  "part_number": "LR078921"
 },
 {
  "part_number": "LR050998"
 },
 {
  "part_number": "LR008843"
 },
 {
  "part_number": "LR071942"
 },
 {
  "part_number": "LR001018"
 },
 {
  "part_number": "1316028"
 },
 {
  "part_number": "FX108046"
 },
 {
  "part_number": "SOD000010"
 },
 {
  "part_number": "LR002876"
 },
 {
  "part_number": "LR073344"
 },
 {
  "part_number": "RBK500210"
 },
 {
  "part_number": "LR016965"
 },
 {
  "part_number": "LR013856"
 },
 {
  "part_number": "LR023443"
 },
 {
  "part_number": "LR134700"
 },
 {
  "part_number": "LR113004"
 },
 {
  "part_number": "LR029078"
 },
 {
  "part_number": "LR113003"
 },
 {
  "part_number": "LR013506"
 },
 {
  "part_number": "LR134696"
 },
 {
  "part_number": "LR078819"
 },
 {
  "part_number": "LR000684"
 },
 {
  "part_number": "LR106494"
 },
 {
  "part_number": "LR027995"
 },
 {
  "part_number": "LR039935"
 },
 {
  "part_number": "LR016176"
 },
 {
  "part_number": "LR138826"
 },
 {
  "part_number": "1311306"
 },
 {
  "part_number": "LR023441"
 },
 {
  "part_number": "LR001174"
 },
 {
  "part_number": "LR032298"
 },
 {
  "part_number": "LR038934"
 },
 {
  "part_number": "LR012844"
 },
 {
  "part_number": "LR002229"
 },
 {
  "part_number": "SPU500040"
 },
 {
  "part_number": "LR133579"
 },
 {
  "part_number": "LR036304"
 },
 {
  "part_number": "LR013857"
 },
 {
  "part_number": "LR023977"
 },
 {
  "part_number": "LR085487"
 },
 {
  "part_number": "LR035493"
 },
 {
  "part_number": "TZB500050"
 },
 {
  "part_number": "PHE000112"
 },
 {
  "part_number": "ANR1864"
 },
 {
  "part_number": "LR041425"
 },
 {
  "part_number": "LR000506"
 },
 {
  "part_number": "LR056285"
 },
 {
  "part_number": "LR030593"
 },
 {
  "part_number": "LR078922"
 },
 {
  "part_number": "LR022300"
 },
 {
  "part_number": "LR066436"
 },
 {
  "part_number": "LR075980"
 },
 {
  "part_number": "LR027123"
 },
 {
  "part_number": "LR095472"
 },
 {
  "part_number": "LR018367"
 },
 {
  "part_number": "LR038607"
 },
 {
  "part_number": "LR052515"
 },
 {
  "part_number": "LR001172"
 },
 {
  "part_number": "LR079909"
 },
 {
  "part_number": "LR048472"
 },
 {
  "part_number": "LR076850"
 },
 {
  "part_number": "LR148836"
 },
 {
  "part_number": "LR051013"
 },
 {
  "part_number": "LR004304"
 },
 {
  "part_number": "LR002626"
 },
 {
  "part_number": "LR032048"
 },
 {
  "part_number": "RYV000010"
 },
 {
  "part_number": "LR010329"
 },
 {
  "part_number": "LR010696"
 },
 {
  "part_number": "LR158113"
 },
 {
  "part_number": "RGD000312"
 },
 {
  "part_number": "LR013022"
 },
 {
  "part_number": "LR100313"
 },
 {
  "part_number": "LR076692"
 },
 {
  "part_number": "LR033029"
 },
 {
  "part_number": "LR001419"
 },
 {
  "part_number": "LR022994"
 },
 {
  "part_number": "LR033303"
 },
 {
  "part_number": "LR011586"
 },
 {
  "part_number": "LR011585"
 },
 {
  "part_number": "LR041681"
 },
 {
  "part_number": "RHF500100"
 },
 {
  "part_number": "QFK500010"
 },
 {
  "part_number": "LR011343"
 },
 {
  "part_number": "LR001624"
 },
 {
  "part_number": "RYP501170"
 },
 {
  "part_number": "FC116216"
 },
 {
  "part_number": "SMN500040"
 },
 {
  "part_number": "LR038632"
 },
 {
  "part_number": "LR002908"
 },
 {
  "part_number": "LR003125"
 },
 {
  "part_number": "LR000578"
 },
 {
  "part_number": "LR122427"
 },
 {
  "part_number": "LR077915"
 },
 {
  "part_number": "LR031668"
 },
 {
  "part_number": "LR061407"
 },
 {
  "part_number": "LR026143"
 },
 {
  "part_number": "LR033302"
 },
 {
  "part_number": "1311318"
 },
 {
  "part_number": "DYA000040"
 },
 {
  "part_number": "SDB000636"
 },
 {
  "part_number": "LR006101"
 },
 {
  "part_number": "LR005165"
 },
 {
  "part_number": "LR002746"
 },
 {
  "part_number": "LR048462"
 },
 {
  "part_number": "LR019984"
 },
 {
  "part_number": "RYH501060"
 },
 {
  "part_number": "LR124504"
 },
 {
  "part_number": "LR031666"
 },
 {
  "part_number": "RYG000384"
 },
 {
  "part_number": "LR114004"
 },
 {
  "part_number": "LR016412"
 },
 {
  "part_number": "LR033027"
 },
 {
  "part_number": "LR016683"
 },
 {
  "part_number": "CLB000010"
 },
 {
  "part_number": "RBK500280"
 },
 {
  "part_number": "LR022852"
 },
 {
  "part_number": "LR001623"
 },
 {
  "part_number": "LR154091"
 },
 {
  "part_number": "LR003157"
 },
 {
  "part_number": "RBK500300"
 },
 {
  "part_number": "LR005483"
 },
 {
  "part_number": "WJI500030"
 },
 {
  "part_number": "LR134692"
 },
 {
  "part_number": "LR048849"
 },
 {
  "part_number": "CFM500010"
 },
 {
  "part_number": "LR072304"
 },
 {
  "part_number": "LR052905"
 },
 {
  "part_number": "LR073340"
 },
 {
  "part_number": "LR012685"
 },
 {
  "part_number": "WCM500080"
 },
 {
  "part_number": "LR123892"
 },
 {
  "part_number": "LR035632"
 },
 {
  "part_number": "LR106593"
 },
 {
  "part_number": "LR013235"
 },
 {
  "part_number": "LR000954"
 },
 {
  "part_number": "RHF000260"
 },
 {
  "part_number": "WEB500300"
 },
 {
  "part_number": "LR110459"
 },
 {
  "part_number": "LR083272"
 },
 {
  "part_number": "LR032360"
 },
 {
  "part_number": "RVW100010"
 },
 {
  "part_number": "LR073372"
 },
 {
  "part_number": "LR028136"
 },
 {
  "part_number": "LR146301"
 },
 {
  "part_number": "1331259"
 },
 {
  "part_number": "LR070359"
 },
 {
  "part_number": "LR090630"
 },
 {
  "part_number": "LR046643"
 },
 {
  "part_number": "LR022099"
 },
 {
  "part_number": "LR075759"
 },
 {
  "part_number": "LR110409"
 },
 {
  "part_number": "LR016655"
 },
 {
  "part_number": "LR092992"
 },
 {
  "part_number": "LR018829"
 },
 {
  "part_number": "LR097165"
 },
 {
  "part_number": "LR051585"
 },
 {
  "part_number": "LR080119"
 },
 {
  "part_number": "LR038533"
 },
 {
  "part_number": "DKW100020"
 },
 {
  "part_number": "LR011038"
 },
 {
  "part_number": "LR049370"
 },
 {
  "part_number": "LR048615"
 },
 {
  "part_number": "LR110782"
 },
 {
  "part_number": "LR022460"
 },
 {
  "part_number": "LR016140"
 },
 {
  "part_number": "LR003787"
 },
 {
  "part_number": "1331267"
 },
 {
  "part_number": "LR051528"
 },
 {
  "part_number": "LR011952"
 },
 {
  "part_number": "LR013151"
 },
 {
  "part_number": "LR064320"
 },
 {
  "part_number": "LR010706"
 },
 {
  "part_number": "LR058010"
 },
 {
  "part_number": "LR026206"
 },
 {
  "part_number": "LR020213"
 },
 {
  "part_number": "LR033471"
 },
 {
  "part_number": "LR002162"
 },
 {
  "part_number": "LR031843"
 },
 {
  "part_number": "LR051012"
 },
 {
  "part_number": "LR051011"
 },
 {
  "part_number": "LR024477"
 },
 {
  "part_number": "LR121039"
 },
 {
  "part_number": "LR022742"
 },
 {
  "part_number": "SMN500030"
 },
 {
  "part_number": "LR148059"
 },
 {
  "part_number": "LR001312"
 },
 {
  "part_number": "LR080116"
 },
 {
  "part_number": "LR072638"
 },
 {
  "part_number": "LR080118"
 },
 {
  "part_number": "LR087351"
 },
 {
  "part_number": "LR031750"
 },
 {
  "part_number": "LR019461"
 },
 {
  "part_number": "LR052059"
 },
 {
  "part_number": "STC1908"
 },
 {
  "part_number": "LR084664"
 },
 {
  "part_number": "LR016869"
 },
 {
  "part_number": "LR148060"
 },
 {
  "part_number": "LR080120"
 },
 {
  "part_number": "RYP500060"
 },
 {
  "part_number": "LR031846"
 },
 {
  "part_number": "LR031845"
 },
 {
  "part_number": "LR044555"
 },
 {
  "part_number": "LR019462"
 },
 {
  "part_number": "LR020489"
 },
 {
  "part_number": "PQG500250"
 },
 {
  "part_number": "LR023175"
 },
 {
  "part_number": "LR001126"
 },
 {
  "part_number": "RYG500220"
 },
 {
  "part_number": "TYP500070"
 },
 {
  "part_number": "FY110056"
 },
 {
  "part_number": "LR070840"
 },
 {
  "part_number": "LR000681"
 },
 {
  "part_number": "FUG500010"
 },
 {
  "part_number": "LR004234"
 },
 {
  "part_number": "LR013234"
 },
 {
  "part_number": "LR158115"
 },
 {
  "part_number": "1102415"
 },
 {
  "part_number": "RGD500140"
 },
 {
  "part_number": "LR045917"
 },
 {
  "part_number": "LR111065"
 },
 {
  "part_number": "LR011694"
 },
 {
  "part_number": "LR041680"
 },
 {
  "part_number": "LR010882"
 },
 {
  "part_number": "LR111341"
 },
 {
  "part_number": "LR022730"
 },
 {
  "part_number": "RYP501110"
 },
 {
  "part_number": "DYF500010"
 },
 {
  "part_number": "KYH500100"
 },
 {
  "part_number": "LR134694"
 },
 {
  "part_number": "LR045540"
 },
 {
  "part_number": "LR016619"
 },
 {
  "part_number": "LR025920"
 },
 {
  "part_number": "LR025565"
 },
 {
  "part_number": "LR006618"
 },
 {
  "part_number": "RBJ500920"
 },
 {
  "part_number": "TZB500100"
 },
 {
  "part_number": "4556038"
 },
 {
  "part_number": "LR122455"
 },
 {
  "part_number": "LR038084"
 },
 {
  "part_number": "QJB500050"
 },
 {
  "part_number": "LR022809"
 },
 {
  "part_number": "LR004532"
 },
 {
  "part_number": "LR108438"
 },
 {
  "part_number": "LR016656"
 },
 {
  "part_number": "LR022953"
 },
 {
  "part_number": "PQG500160"
 },
 {
  "part_number": "LR045473"
 },
 {
  "part_number": "LR023142"
 },
 {
  "part_number": "LR022718"
 },
 {
  "part_number": "FC112267"
 },
 {
  "part_number": "PNH500371"
 },
 {
  "part_number": "LR051702"
 },
 {
  "part_number": "LR025664"
 },
 {
  "part_number": "LR010789"
 },
 {
  "part_number": "LR002610"
 },
 {
  "part_number": "KHC000050"
 },
 {
  "part_number": "LR003154"
 },
 {
  "part_number": "LR134882"
 },
 {
  "part_number": "LR044565"
 },
 {
  "part_number": "LR002576"
 },
 {
  "part_number": "YDB500301PMA"
 },
 {
  "part_number": "LR061388"
 },
 {
  "part_number": "LR014359"
 },
 {
  "part_number": "LR005896"
 },
 {
  "part_number": "LR011721"
 },
 {
  "part_number": "LR005371"
 },
 {
  "part_number": "LR146341"
 },
 {
  "part_number": "TZB500030"
 },
 {
  "part_number": "LR078012"
 },
 {
  "part_number": "LR016621"
 },
 {
  "part_number": "LR025083"
 },
 {
  "part_number": "LR007206"
 },
 {
  "part_number": "LR007205"
 },
 {
  "part_number": "LR000877"
 },
 {
  "part_number": "LR036058"
 },
 {
  "part_number": "RBK500170"
 },
 {
  "part_number": "DKC000040"
 },
 {
  "part_number": "LR050753"
 },
 {
  "part_number": "TYP500050"
 },
 {
  "part_number": "FN106046"
 },
 {
  "part_number": "PNH500025"
 },
 {
  "part_number": "LR023208"
 },
 {
  "part_number": "LR022515"
 },
 {
  "part_number": "LR035502"
 },
 {
  "part_number": "RBX500432"
 },
 {
  "part_number": "LR006348"
 },
 {
  "part_number": "LR020548"
 },
 {
  "part_number": "LR019117"
 },
 {
  "part_number": "LR044466"
 },
 {
  "part_number": "LR012047"
 },
 {
  "part_number": "RYP501050"
 },
 {
  "part_number": "LR005738"
 },
 {
  "part_number": "4537592"
 },
 {
  "part_number": "LR097980"
 },
 {
  "part_number": "LR134697"
 },
 {
  "part_number": "LR010965"
 },
 {
  "part_number": "1331270"
 },
 {
  "part_number": "LR058009"
 },
 {
  "part_number": "LR155579"
 },
 {
  "part_number": "1311338"
 },
 {
  "part_number": "LR005976"
 },
 {
  "part_number": "PQH500090"
 },
 {
  "part_number": "PNH500361"
 },
 {
  "part_number": "LR051700"
 },
 {
  "part_number": "LR166341"
 },
 {
  "part_number": "LR020367"
 },
 {
  "part_number": "LR003152"
 },
 {
  "part_number": "LR006115"
 },
 {
  "part_number": "LR092258"
 },
 {
  "part_number": "DKB500680"
 },
 {
  "part_number": "LR154776"
 },
 {
  "part_number": "RYP501120"
 },
 {
  "part_number": "FS108186"
 },
 {
  "part_number": "LR105956"
 },
 {
  "part_number": "LR110504"
 },
 {
  "part_number": "LR061463"
 },
 {
  "part_number": "LR011722"
 },
 {
  "part_number": "PQH500130"
 },
 {
  "part_number": "LR033226"
 },
 {
  "part_number": "AZP500060"
 },
 {
  "part_number": "LR039527"
 },
 {
  "part_number": "LR024508"
 },
 {
  "part_number": "LR032839"
 },
 {
  "part_number": "LR019960"
 },
 {
  "part_number": "WCM500120"
 },
 {
  "part_number": "LR016139"
 },
 {
  "part_number": "LR019464"
 },
 {
  "part_number": "LR019463"
 },
 {
  "part_number": "LYR500010"
 },
 {
  "part_number": "LR056305"
 },
 {
  "part_number": "LR056308"
 },
 {
  "part_number": "LR024506"
 },
 {
  "part_number": "LR000073"
 },
 {
  "part_number": "FY112056"
 },
 {
  "part_number": "LR000753"
 },
 {
  "part_number": "CYC000010"
 },
 {
  "part_number": "EYC106710"
 },
 {
  "part_number": "PCD500030"
 },
 {
  "part_number": "LR001310"
 },
 {
  "part_number": "LR013697"
 },
 {
  "part_number": "LR078478"
 },
 {
  "part_number": "LR003153"
 },
 {
  "part_number": "LR019019"
 },
 {
  "part_number": "LR038051"
 },
 {
  "part_number": "LR031593"
 },
 {
  "part_number": "LR028235"
 },
 {
  "part_number": "LR100039"
 },
 {
  "part_number": "KYG000230"
 },
 {
  "part_number": "LR033698"
 },
 {
  "part_number": "RYH500170"
 },
 {
  "part_number": "LR083610"
 },
 {
  "part_number": "LR034262"
 },
 {
  "part_number": "LR034323"
 },
 {
  "part_number": "LR023050"
 },
 {
  "part_number": "LR004250"
 },
 {
  "part_number": "LR016138"
 },
 {
  "part_number": "LR002609"
 },
 {
  "part_number": "LR078476"
 },
 {
  "part_number": "LR052514"
 },
 {
  "part_number": "LR024474"
 },
 {
  "part_number": "LR014145"
 },
 {
  "part_number": "LR021678"
 },
 {
  "part_number": "LR015144"
 },
 {
  "part_number": "LR121267"
 },
 {
  "part_number": "LR116732"
 },
 {
  "part_number": "SEE500020"
 },
 {
  "part_number": "LR023290"
 },
 {
  "part_number": "LR006205"
 },
 {
  "part_number": "LR083938"
 },
 {
  "part_number": "LR036090"
 },
 {
  "part_number": "LR003828"
 },
 {
  "part_number": "LR004319"
 },
 {
  "part_number": "LR009028"
 },
 {
  "part_number": "KHC000060"
 },
 {
  "part_number": "RUE000010"
 },
 {
  "part_number": "LR025011"
 },
 {
  "part_number": "LR135810"
 },
 {
  "part_number": "LR146343"
 },
 {
  "part_number": "LR125292"
 },
 {
  "part_number": "LR154485"
 },
 {
  "part_number": "LR154635"
 },
 {
  "part_number": "LR154636"
 },
 {
  "part_number": "LR078913"
 },
 {
  "part_number": "LR113200"
 }
]
